term_assistant/__init__.py
term_assistant/__main__.py
term_assistant/config.py
term_assistant/llm.py
term_assistant/logging.py
term_assistant/terminal.py
term_assistant/tools.py
term_assistant-0.1.0.dist-info/METADATA
term_assistant-0.1.0.dist-info/WHEEL
term_assistant-0.1.0.dist-info/entry_points.txt
term_assistant-0.1.0.dist-info/RECORD
