Metadata-Version: 2.1
Name: term-assistant
Version: 0.1.0
Summary: 
Keywords: llm,terminal,cli
Author: SiriusKoan
Author-email: me@siriuskoan.one
Requires-Python: >=3.10,<4.0
Classifier: Programming Language :: Python :: 3
Classifier: Programming Language :: Python :: 3.10
Classifier: Programming Language :: Python :: 3.11
Classifier: Programming Language :: Python :: 3.12
Classifier: Programming Language :: Python :: 3.13
Requires-Dist: click (>=8.1.8,<9.0.0)
Requires-Dist: colorama (>=0.4.6,<0.5.0)
Requires-Dist: grpcio (==1.67.1)
Requires-Dist: grpcio-status (==1.67.1)
Requires-Dist: libtmux (>=0.40.1,<0.41.0)
Requires-Dist: litellm (==1.55.12)
Requires-Dist: pyyaml (>=6.0.2,<7.0.0)
